README.md
setup.cfg
setup.py
pymainichigo/__init__.py
pymainichigo/desktop.py
pymainichigo/goban.pde.template
pymainichigo/main.py
pymainichigo/selector.py
pymainichigo/test.sgf
pymainichigo.egg-info/PKG-INFO
pymainichigo.egg-info/SOURCES.txt
pymainichigo.egg-info/dependency_links.txt
pymainichigo.egg-info/entry_points.txt
pymainichigo.egg-info/requires.txt
pymainichigo.egg-info/top_level.txt
pymainichigo/renderer/__init__.py
pymainichigo/renderer/processing.py
pymainichigo/sgf/__init__.py
pymainichigo/sgf/gogame.py