Metadata-Version: 1.1
Name: pymainichigo
Version: 1.0.1
Summary: Wallpaper generator for Go/Baduk/Weiqi positions
Home-page: https://github.com/apetresc/pymainichigo
Author: Adrian Petrescu
Author-email: apetresc@gmail.com
License: GPL
Platform: UNKNOWN
Classifier: Development Status :: 4 - Beta
Classifier: Programming Language :: Python :: 3.6
